dpop/__init__.py
dpop/dpop.py
dpop-0.0.2.dist-info/LICENSE
dpop-0.0.2.dist-info/METADATA
dpop-0.0.2.dist-info/WHEEL
dpop-0.0.2.dist-info/entry_points.txt
dpop-0.0.2.dist-info/top_level.txt
dpop-0.0.2.dist-info/RECORD
